[
{"title":"SP","nextlevel":"prefeitos_partidos","dados2008":[69,70,0],"dados2012":[88,91],"valorFinal2008":[70]},
{"title":"MG","nextlevel":"prefeitos_partidos","dados2008":[119,121,0],"dados2012":[117,119],"valorFinal2008":[120]},
{"title":"RJ","nextlevel":"prefeitos_partidos","dados2008":[33,35,0],"dados2012":[22,26],"valorFinal2008":[35]},
{"title":"BA","nextlevel":"prefeitos_partidos","dados2008":[114,115,0],"dados2012":[44,45],"valorFinal2008":[115]},
{"title":"RS","nextlevel":"prefeitos_partidos","dados2008":[142,143,0],"dados2012":[132,132],"valorFinal2008":[143]},
{"title":"PR","nextlevel":"prefeitos_partidos","dados2008":[135,135,0],"dados2012":[56,56],"valorFinal2008":[135]},
{"title":"PE","nextlevel":"prefeitos_partidos","dados2008":[10,10,0],"dados2012":[7,7],"valorFinal2008":[10]},
{"title":"CE","nextlevel":"prefeitos_partidos","dados2008":[33,33,0],"dados2012":[21,21],"valorFinal2008":[33]},
{"title":"PA","nextlevel":"prefeitos_partidos","dados2008":[39,40,0],"dados2012":[28,28],"valorFinal2008":[39]},
{"title":"SC","nextlevel":"prefeitos_partidos","dados2008":[109,110,0],"dados2012":[105,107],"valorFinal2008":[110]},
{"title":"MA","nextlevel":"prefeitos_partidos","dados2008":[16,16,0],"dados2012":[47,47],"valorFinal2008":[16]},
{"title":"GO","nextlevel":"prefeitos_partidos","dados2008":[59,60,0],"dados2012":[57,57],"valorFinal2008":[59]},
{"title":"PB","nextlevel":"prefeitos_partidos","dados2008":[58,59,0],"dados2012":[58,59],"valorFinal2008":[59]},
{"title":"Outros","nextlevel":"prefeitos_pmdb_estados_outros","dados2008":[257,258,0],"dados2012":[238,241],"valorFinal2008":[257]}
]
